abq_post_analytics_extension/__init__.py
abq_post_analytics_extension/default_config.py
abq_post_analytics_extension/core/__init__.py
abq_post_analytics_extension/core/access.py
abq_post_analytics_extension/core/analysis/__init__.py
abq_post_analytics_extension/core/analysis/analyzer.py
abq_post_analytics_extension/core/analysis/base.py
abq_post_analytics_extension/core/analysis/shap_selection_analyzer.py
abq_post_analytics_extension/utils/__init__.py
abq_post_analytics_extension/utils/cae_submit.py
abq_post_analytics_extension/utils/file_operations.py
abq_post_analytics_extension/utils/logger_and_print.py
abq_post_analytics_extension/utils/misc_utils.py
abq_post_analytics_extension/utils/scientific_computing.py
abq_post_analytics_extension/utils/system_utilities.py
abq_post_analytics_extension/utils/test_tools.py
abq_post_analytics_extension/utils/text_files_organization.py
abq_post_analytics_extension-1.0.1.dist-info/licenses/LICENSE
abq_post_analytics_extension-1.0.1.dist-info/METADATA
abq_post_analytics_extension-1.0.1.dist-info/WHEEL
abq_post_analytics_extension-1.0.1.dist-info/top_level.txt
abq_post_analytics_extension-1.0.1.dist-info/RECORD
