Metadata-Version: 2.4
Name: abq_post_analytics_extension
Version: 1.0.1
Summary: ABQ 后处理扩展
Home-page: https://gitee.com/FeiI8/abq_postprocessings.git
Author: FeiI8
Author-email: 2286528584@qq.com
License: GPL-3.0
Classifier: License :: OSI Approved :: GNU General Public License v3 (GPLv3)
License-File: LICENSE
Dynamic: author
Dynamic: author-email
Dynamic: classifier
Dynamic: description
Dynamic: description-content-type
Dynamic: home-page
Dynamic: license
Dynamic: license-file
Dynamic: summary
